fotoparadies/__init__.py
fotoparadies/__main__.py
fotoparadies/api.py
fotoparadies_orders_cli_avra-0.1a1.data/scripts/fotoparadies
fotoparadies_orders_cli_avra-0.1a1.dist-info/LICENSE
fotoparadies_orders_cli_avra-0.1a1.dist-info/METADATA
fotoparadies_orders_cli_avra-0.1a1.dist-info/WHEEL
fotoparadies_orders_cli_avra-0.1a1.dist-info/top_level.txt
fotoparadies_orders_cli_avra-0.1a1.dist-info/RECORD
