Metadata-Version: 2.1
Name: fotoparadies-orders-cli-avra
Version: 0.1a1
Summary: Unofficial command line interface for keeping track of dm Fotoparadies orders.
Home-page: https://github.com/StefanAvra/fotoparadies-orders-cli
Author: Stefan Avramescu
Author-email: stefan.avra@gmail.com
License: UNKNOWN
Platform: UNKNOWN
Classifier: Programming Language :: Python :: 3
Classifier: License :: OSI Approved :: MIT License
Classifier: Operating System :: OS Independent
Requires-Python: >=3.6
